fastpluggy_plugin/memory_analyzer/__init__.py
fastpluggy_plugin/memory_analyzer/config.py
fastpluggy_plugin/memory_analyzer/middleware.py
fastpluggy_plugin/memory_analyzer/plugin.py
fastpluggy_plugin/memory_analyzer/store.py
fastpluggy_plugin/memory_analyzer/router/__init__.py
fastpluggy_plugin/memory_analyzer/router/endpoints_memory.py
fastpluggy_plugin/memory_analyzer/router/psutil_analyzer.py
fastpluggy_plugin/memory_analyzer/templates/endpoints_dashboard.html.j2
fastpluggy_plugin/memory_analyzer/templates/endpoints_detail.html.j2
fastpluggy_plugin/memory_analyzer/templates/memory_current.html.j2
fastpluggy_plugin/memory_analyzer/templates/psutil_analyzer.html.j2
fastpluggy_plugin/memory_analyzer/widgets/__init__.py
fastpluggy_plugin/memory_analyzer/widgets/psutil_analyzer.py
fastpluggy_memory_analyzer-0.0.8.dist-info/METADATA
fastpluggy_memory_analyzer-0.0.8.dist-info/WHEEL
fastpluggy_memory_analyzer-0.0.8.dist-info/entry_points.txt
fastpluggy_memory_analyzer-0.0.8.dist-info/top_level.txt
fastpluggy_memory_analyzer-0.0.8.dist-info/RECORD
