Metadata-Version: 2.4
Name: fastpluggy-memory-analyzer
Version: 0.0.8
Summary: Memory Analyzer plugin for Fastpluggy
Author: FastPluggy Team
Requires-Python: >=3.10
Requires-Dist: FastPluggy>=0.2.50
Requires-Dist: psutil
Requires-Dist: pympler
